dbtpurview/__init__.py
dbtpurview/main.py
dbt_purview_integration-1.3.dist-info/METADATA
dbt_purview_integration-1.3.dist-info/WHEEL
dbt_purview_integration-1.3.dist-info/entry_points.txt
dbt_purview_integration-1.3.dist-info/top_level.txt
dbt_purview_integration-1.3.dist-info/RECORD
