Metadata-Version: 2.1
Name: dbt-purview-integration
Version: 1.3
Requires-Dist: click
Requires-Dist: requests
Requires-Dist: apache-airflow
